paam/__init__.py
paam/__version__.py
python_attribute_access_modifiers-1.0.0.dist-info/LICENSE
python_attribute_access_modifiers-1.0.0.dist-info/METADATA
python_attribute_access_modifiers-1.0.0.dist-info/WHEEL
python_attribute_access_modifiers-1.0.0.dist-info/top_level.txt
python_attribute_access_modifiers-1.0.0.dist-info/RECORD
