Metadata-Version: 2.1
Name: python-attribute-access-modifiers
Version: 1.0.0
Summary: UNKNOWN
Home-page: https://github.com/2435191/python-attribute-access-modifiers
Author: Will Bradley
Author-email: derivativedude123@gmail.com
License: License :: OSI Approved :: MIT License
Platform: UNKNOWN
License-File: LICENSE
Requires-Dist: importlib ; python_version >= "3.8"
